plover_start_words/__init__.py
plover_start_words/meta.py
plover_start_words-1.0.2.dist-info/LICENSE.txt
plover_start_words-1.0.2.dist-info/METADATA
plover_start_words-1.0.2.dist-info/WHEEL
plover_start_words-1.0.2.dist-info/top_level.txt
plover_start_words-1.0.2.dist-info/zip-safe
plover_start_words-1.0.2.dist-info/RECORD
