Metadata-Version: 2.1
Name: plover-start-words
Version: 1.0.2
Summary: Plugin for assigning strokes to different output if it starts or not a word
Home-page: https://github.com/nvdaes/plover_start_words
Author: Noelia Ruiz
Author-email: nrm1977@gmail.com
License: GNU General Public License v3 or later (GPLv3+)
Project-URL: Source Code, https://github.com/nvdaes/plover_start_words
Project-URL: Issue Tracker, https://github.com/nvdaes/plover_start_words/issues
Keywords: plover plover_plugin
Platform: UNKNOWN
Classifier: Development Status :: 5 - Production/Stable
Classifier: Environment :: Plugins
Classifier: Intended Audience :: End Users/Desktop
Classifier: License :: OSI Approved :: GNU General Public License v3 or later (GPLv3+)
Classifier: Operating System :: OS Independent
Classifier: Programming Language :: Python :: 3
Classifier: Programming Language :: Python :: 3.6
Classifier: Programming Language :: Python :: 3.7
Classifier: Programming Language :: Python :: 3.8
Classifier: Programming Language :: Python :: 3.9
Requires-Python: >=3.6
Requires-Dist: plover (>=4.0.0.dev9)
Provides-Extra: lint
Requires-Dist: flake8 (~=3.7.7) ; extra == 'lint'
Requires-Dist: flake8-tabs (==2.1.0) ; extra == 'lint'
